py_ax_s/__init__.py
py_ax_s/api.py
py_ax_s-0.1.2.dist-info/WHEEL
py_ax_s-0.1.2.dist-info/METADATA
py_ax_s-0.1.2.dist-info/RECORD
