Metadata-Version: 2.1
Name: py-ax-s
Version: 0.1.2
Summary: A Python client for the ax-s API.
Home-page: UNKNOWN
License: UNKNOWN
Author: elliott-maguire
Author-email: elliott.maguire@ax-s.io
Requires-Python: >=3.7,<4.0
Classifier: Programming Language :: Python :: 3
Classifier: Programming Language :: Python :: 3.7
Requires-Dist: requests (>=2.21,<3.0)
